Semester 3/DSD/Week08/q5.v
module q5(w,y);
input [15:0] w;
output reg [3:0] y;
integer i;
always @(w)
begin 
        for (i=0; i<16; i+=1)
        begin	
        	if (w[i]==1) y=i;
        end
end
endmodule

Semester 3/DSD/Week08/q5_tb.v
`timescale 1ns/1ns
`include "q5.v"

module q5_tb;
reg [15:0] w;
wire [3:0] y;

q5 uut(w,y);
initial begin
	$dumpfile("q5_tb.vcd");
    	$dumpvars(0,q5_tb);
    	w = 16'b1000000000000000; #20; w = 16'b0100000000000000; #20;
    	w = 16'b0010000000000000; #20; w = 16'b0001000000000000; #20;
    	w = 16'b0000100000000000; #20; w = 16'b0000010000000000; #20;
    	w = 16'b0000001000000000; #20; w = 16'b0000000100000000; #20;
    	w = 16'b0000000010000000; #20; w = 16'b0000000001000000; #20;
    	w = 16'b0000000000100000; #20; w = 16'b0000000000010000; #20;
    	w = 16'b0000000000001000; #20; w = 16'b0000000000000100; #20;
    	w = 16'b0000000000000010; #20; w = 16'b0000000000000001; #20;
	$display("Test Complete");
end
endmodule

Semester 3/DSD/Week08/q5_tb.vcd
$date
	Thu Oct 27 16:54:40 2022
$end
$version
	Icarus Verilog
$end
$timescale
	1ns
$end
$scope module q5_tb $end
$var wire 4 ! y [3:0] $end
$var reg 16 " w [15:0] $end
$scope module uut $end
$var wire 16 # w [15:0] $end
$var reg 4 $ y [3:0] $end
$var integer 32 % i [31:0] $end
$upscope $end
$upscope $end
$enddefinitions $end
#0
$dumpvars
b10000 %
b1111 $
b1000000000000000 #
b1000000000000000 "
b1111 !
$end
#20
b1110 !
b1110 $
b10000 %
b100000000000000 "
b100000000000000 #
#40
b1101 !
b1101 $
b10000 %
b10000000000000 "
b10000000000000 #
#60
b1100 !
b1100 $
b10000 %
b1000000000000 "
b1000000000000 #
#80
b1011 !
b1011 $
b10000 %
b100000000000 "
b100000000000 #
#100
b1010 !
b1010 $
b10000 %
b10000000000 "
b10000000000 #
#120
b1001 !
b1001 $
b10000 %
b1000000000 "
b1000000000 #
#140
b1000 !
b1000 $
b10000 %
b100000000 "
b100000000 #
#160
b111 !
b111 $
b10000 %
b10000000 "
b10000000 #
#180
b110 !
b110 $
b10000 %
b1000000 "
b1000000 #
#200
b101 !
b101 $
b10000 %
b100000 "
b100000 #
#220
b100 !
b100 $
b10000 %
b10000 "
b10000 #
#240
b11 !
b11 $
b10000 %
b1000 "
b1000 #
#260
b10 !
b10 $
b10000 %
b100 "
b100 #
#280
b1 !
b1 $
b10000 %
b10 "
b10 #
#300
b0 !
b0 $
b10000 %
b1 "
b1 #
