Semester 3/DSD/Week02/ex2b.v
module ex2b(a,b,c,d,f1,f2);
input a,b,c,d;
output f1,f2;
or(k1,~a,~b,c);
or(k2,~a,b,~d);
or(k3,b,~c,d);
or(k4,a,~b,~c);
and(f1,k1,k2,k3,k4);
assign f2=((~a|~b|c)&(~a|b|~d)&(b|~c|d)&(a|~b|~c));
endmodule

Semester 3/DSD/Week02/ex2b_tb.v
`timescale 1ns/1ns
`include "ex2b.v"

module ex2b_tb;

reg a,b,c,d;
wire f1,f2;

ex2b ex(a,b,c,d,f1,f2);
initial begin
	$dumpfile("ex2b_tb.vcd");
	$dumpvars(0,ex2b_tb);
	a=0; b=0; c=0; d=0; #20;
	a=0; b=0; c=0; d=1; #20;
	a=0; b=0; c=1; d=0; #20;
	a=0; b=0; c=1; d=1; #20;
	a=0; b=1; c=0; d=0; #20;
	a=0; b=1; c=0; d=1; #20;
	a=0; b=1; c=1; d=0; #20;
	a=0; b=1; c=1; d=1; #20;
	a=1; b=0; c=0; d=0; #20;
	a=1; b=0; c=0; d=1; #20;
	a=1; b=0; c=1; d=0; #20;
	a=1; b=0; c=1; d=1; #20;
	a=1; b=1; c=0; d=0; #20;
	a=1; b=1; c=0; d=1; #20;
	a=1; b=1; c=1; d=0; #20;
	a=1; b=1; c=1; d=1; #20;
	$display ("Test Complete");
	
	end 
	endmodule

Semester 3/DSD/Week02/ex2b_tb.vcd
$date
	Thu Sep  1 15:06:02 2022
$end
$version
	Icarus Verilog
$end
$timescale
	1ns
$end
$scope module ex2b_tb $end
$var wire 1 ! f2 $end
$var wire 1 " f1 $end
$var reg 1 # a $end
$var reg 1 $ b $end
$var reg 1 % c $end
$var reg 1 & d $end
$scope module ex $end
$var wire 1 # a $end
$var wire 1 $ b $end
$var wire 1 % c $end
$var wire 1 & d $end
$var wire 1 " f1 $end
$var wire 1 ! f2 $end
$var wire 1 ' k1 $end
$var wire 1 ( k2 $end
$var wire 1 ) k3 $end
$var wire 1 * k4 $end
$upscope $end
$upscope $end
$enddefinitions $end
#0
$dumpvars
1*
1)
1(
1'
0&
0%
0$
0#
1"
1!
$end
#20
1&
#40
0!
0"
0)
0&
1%
#60
1!
1"
1)
1&
#80
0&
0%
1$
#100
1&
#120
0"
0!
0*
0&
1%
#140
1&
#160
1!
1"
1(
1)
1*
0&
0%
0$
1#
#180
0!
0"
0(
1&
#200
1(
0)
0&
1%
#220
0!
0(
0"
1)
1&
#240
0!
0'
1(
0&
0%
1$
#260
1&
#280
1!
1"
1'
0&
1%
#300
1&
