Semester 3/DSD/Week02/ex3.v
module ex3(a,b,c,d,f1,f2);
input a,b,c,d;
output f1,f2;
and(k1,a,b,d);
and(k2,a,c,d);
and(k3,a,b,c);
and(k4,b,c,d);
or(f1,k1,k2,k3,k4);
assign f2= ((a&b&c)|(a&b&d)|(a&c&d)|(b&c&d));
endmodule

Semester 3/DSD/Week02/ex3_tb.v
`timescale 1ns/1ns
`include "ex3.v"

module ex3_tb;

reg a,b,c,d;
wire f1,f2;

ex3 ex(a,b,c,d,f1,f2);
initial begin
	$dumpfile("ex3_tb.vcd");
	$dumpvars(0,ex3_tb);
	a=0; b=0; c=0; d=0; #20;
	a=0; b=0; c=0; d=1; #20;
	a=0; b=0; c=1; d=0; #20;
	a=0; b=0; c=1; d=1; #20;
	a=0; b=1; c=0; d=0; #20;
	a=0; b=1; c=0; d=1; #20;
	a=0; b=1; c=1; d=0; #20;
	a=0; b=1; c=1; d=1; #20;
	a=1; b=0; c=0; d=0; #20;
	a=1; b=0; c=0; d=1; #20;
	a=1; b=0; c=1; d=0; #20;
	a=1; b=0; c=1; d=1; #20;
	a=1; b=1; c=0; d=0; #20;
	a=1; b=1; c=0; d=1; #20;
	a=1; b=1; c=1; d=0; #20;
	a=1; b=1; c=1; d=1; #20;
	$display ("Test Complete");
	
	end 
	endmodule

Semester 3/DSD/Week02/ex3_tb.vcd
$date
	Thu Sep  1 16:37:12 2022
$end
$version
	Icarus Verilog
$end
$timescale
	1ns
$end
$scope module ex3_tb $end
$var wire 1 ! f2 $end
$var wire 1 " f1 $end
$var reg 1 # a $end
$var reg 1 $ b $end
$var reg 1 % c $end
$var reg 1 & d $end
$scope module ex $end
$var wire 1 # a $end
$var wire 1 $ b $end
$var wire 1 % c $end
$var wire 1 & d $end
$var wire 1 " f1 $end
$var wire 1 ! f2 $end
$var wire 1 ' k1 $end
$var wire 1 ( k2 $end
$var wire 1 ) k3 $end
$var wire 1 * k4 $end
$upscope $end
$upscope $end
$enddefinitions $end
#0
$dumpvars
0*
0)
0(
0'
0&
0%
0$
0#
0"
0!
$end
#20
1&
#40
0&
1%
#60
1&
#80
0&
0%
1$
#100
1&
#120
0&
1%
#140
1"
1!
1*
1&
#160
0!
0"
0*
0&
0%
0$
1#
#180
1&
#200
0&
1%
#220
1!
1"
1(
1&
#240
0!
0"
0(
0&
0%
1$
#260
1!
1"
1'
1&
#280
0'
1)
0&
1%
#300
1'
1(
1*
1&
