Semester 3/DSD/Week06/mux16to1case.v
module mux16to1case(W,S,f);
input [0:15] W;
input [3:0] S;
output f;
wire [0:1] k0;
mux8to1 stg0 (W[0:7], S[2:0], k0[0]);
mux8to1 stg1 (W[8:15], S[2:0], k0[1]);
mux2to1 stg2 (k0[0:1], S[3], f);
endmodule

module mux8to1(w1,s1,f1);
input [0:7] w1;
input [2:0] s1;
output f1;
reg f1;
always @(w1 or s1)
case (s1)
0: f1=w1[0]; 1: f1=w1[1];
2: f1=w1[2]; 3: f1=w1[3];
4: f1=w1[4]; 5: f1=w1[5];
6: f1=w1[6]; 7: f1=w1[7];
endcase
endmodule

module mux2to1(w,s,f0);
input [0:1] w;
input s;
output f0;
reg f0;
always @(w or s)
case (s)
0: f0 = w[0];
1: f0 = w[1];
endcase
endmodule

Semester 3/DSD/Week06/mux16to1case_tb.v
`timescale 1ns/1ns
`include "mux16to1case.v"

module mux16to1case_tb;
reg [0:15]W;
reg [3:0]S;
wire f;

mux16to1case uut(W,S,f);
initial begin 
	$dumpfile("mux16to1case_tb.vcd");
	$dumpvars(0,mux16to1case_tb);
	W=16'b1010101010101010;
	S=4'b0000;#20;
	S=4'b0001;#20;
	S=4'b0010;#20;
	S=4'b0011;#20;
	S=4'b0100;#20;
	S=4'b0101;#20;
	S=4'b0110;#20;
	S=4'b0111;#20;
	S=4'b1000;#20;
	S=4'b1001;#20;
	S=4'b1010;#20;
	S=4'b1011;#20;
	S=4'b1100;#20;
	S=4'b1101;#20;
	S=4'b1110;#20;
	S=4'b1111;#20;
	$display("Test Complete");	
end 
endmodule

Semester 3/DSD/Week06/mux16to1case_tb.vcd
$date
	Thu Oct  6 15:57:43 2022
$end
$version
	Icarus Verilog
$end
$timescale
	1ns
$end
$scope module mux16to1case_tb $end
$var wire 1 ! f $end
$var reg 4 " S [3:0] $end
$var reg 16 # W [0:15] $end
$scope module uut $end
$var wire 4 $ S [3:0] $end
$var wire 16 % W [0:15] $end
$var wire 2 & k0 [0:1] $end
$var wire 1 ! f $end
$scope module stg0 $end
$var wire 3 ' s1 [2:0] $end
$var wire 8 ( w1 [0:7] $end
$var reg 1 ) f1 $end
$upscope $end
$scope module stg1 $end
$var wire 3 * s1 [2:0] $end
$var wire 8 + w1 [0:7] $end
$var reg 1 , f1 $end
$upscope $end
$scope module stg2 $end
$var wire 1 - s $end
$var wire 2 . w [0:1] $end
$var reg 1 ! f0 $end
$upscope $end
$upscope $end
$upscope $end
$enddefinitions $end
#0
$dumpvars
b11 .
0-
1,
b10101010 +
b0 *
1)
b10101010 (
b0 '
b11 &
b1010101010101010 %
b0 $
b1010101010101010 #
b0 "
1!
$end
#20
0!
0)
b0 &
b0 .
0,
b1 '
b1 *
b1 "
b1 $
#40
1!
1)
b11 &
b11 .
1,
b10 '
b10 *
b10 "
b10 $
#60
0!
0)
b0 &
b0 .
0,
b11 '
b11 *
b11 "
b11 $
#80
1!
1)
b11 &
b11 .
1,
b100 '
b100 *
b100 "
b100 $
#100
0!
0)
b0 &
b0 .
0,
b101 '
b101 *
b101 "
b101 $
#120
1!
1)
b11 &
b11 .
1,
b110 '
b110 *
b110 "
b110 $
#140
0!
0)
b0 &
b0 .
0,
b111 '
b111 *
b111 "
b111 $
#160
1!
1)
b11 &
b11 .
1,
b0 '
b0 *
1-
b1000 "
b1000 $
#180
0!
0)
b0 &
b0 .
0,
b1 '
b1 *
b1001 "
b1001 $
#200
1!
1)
b11 &
b11 .
1,
b10 '
b10 *
b1010 "
b1010 $
#220
0!
0)
b0 &
b0 .
0,
b11 '
b11 *
b1011 "
b1011 $
#240
1!
1)
b11 &
b11 .
1,
b100 '
b100 *
b1100 "
b1100 $
#260
0!
0)
b0 &
b0 .
0,
b101 '
b101 *
b1101 "
b1101 $
#280
1!
1)
b11 &
b11 .
1,
b110 '
b110 *
b1110 "
b1110 $
#300
0!
0)
b0 &
b0 .
0,
b111 '
b111 *
b1111 "
b1111 $
