Semester 3/DSD/Week06/mux16to1.v
module mux16to1(W,S,f);
input [0:15] W;
input [3:0] S;
output f;
wire [0:3] k;
mux4to1 stage0 (W[0:3], S[1:0], k[0]);
mux4to1 stage1 (W[4:7], S[1:0], k[1]);
mux4to1 stage2 (W[8:11], S[1:0], k[2]);
mux4to1 stage3 (W[12:15], S[1:0], k[3]);
mux4to1 stage4 (k[0:3], S[3:2], f);
endmodule

module mux4to1(w,s,f1);
input [0:3] w;
input [1:0] s;
output f1;
assign f1 = s[1] ? (s[0] ? w[3]:w[2]) : (s[0] ? w[1]:w[0]);
endmodule

Semester 3/DSD/Week06/mux16to1_tb.v
`timescale 1ns/1ns
`include "mux16to1.v"

module mux16to1_tb;
reg [0:15]W;
reg [3:0]S;
wire f;

mux16to1 uut(W,S,f);
initial begin 
	$dumpfile("mux16to1_tb.vcd");
	$dumpvars(0,mux16to1_tb);
	W=16'b1010101010101010;
	S=4'b0000;#20; S=4'b0001;#20;
	S=4'b0010;#20; S=4'b0011;#20;
	S=4'b0100;#20; S=4'b0101;#20;
	S=4'b0110;#20; S=4'b0111;#20;
	S=4'b1000;#20; S=4'b1001;#20;
	S=4'b1010;#20; S=4'b1011;#20;
	S=4'b1100;#20; S=4'b1101;#20;
	S=4'b1110;#20; S=4'b1111;#20;
	$display("Test Complete");	
end 
endmodule

Semester 3/DSD/Week06/mux16to1_tb.vcd
$date
	Thu Oct  6 14:32:12 2022
$end
$version
	Icarus Verilog
$end
$timescale
	1ns
$end
$scope module mux16to1_tb $end
$var wire 1 ! f $end
$var reg 4 " S [3:0] $end
$var reg 16 # W [0:15] $end
$scope module uut $end
$var wire 4 $ S [3:0] $end
$var wire 16 % W [0:15] $end
$var wire 4 & k [0:3] $end
$var wire 1 ! f $end
$scope module stage0 $end
$var wire 2 ' s [1:0] $end
$var wire 4 ( w [0:3] $end
$var wire 1 ) f1 $end
$upscope $end
$scope module stage1 $end
$var wire 2 * s [1:0] $end
$var wire 4 + w [0:3] $end
$var wire 1 , f1 $end
$upscope $end
$scope module stage2 $end
$var wire 2 - s [1:0] $end
$var wire 4 . w [0:3] $end
$var wire 1 / f1 $end
$upscope $end
$scope module stage3 $end
$var wire 2 0 s [1:0] $end
$var wire 4 1 w [0:3] $end
$var wire 1 2 f1 $end
$upscope $end
$scope module stage4 $end
$var wire 2 3 s [1:0] $end
$var wire 4 4 w [0:3] $end
$var wire 1 ! f1 $end
$upscope $end
$upscope $end
$upscope $end
$enddefinitions $end
#0
$dumpvars
b1111 4
b0 3
12
b1010 1
b0 0
1/
b1010 .
b0 -
1,
b1010 +
b0 *
1)
b1010 (
b0 '
b1111 &
b1010101010101010 %
b0 $
b1010101010101010 #
b0 "
1!
$end
#20
0!
0)
0,
0/
b0 &
b0 4
02
b1 '
b1 *
b1 -
b1 0
b1 "
b1 $
#40
1!
1)
1,
1/
b1111 &
b1111 4
12
b10 '
b10 *
b10 -
b10 0
b10 "
b10 $
#60
0!
0)
0,
0/
b0 &
b0 4
02
b11 '
b11 *
b11 -
b11 0
b11 "
b11 $
#80
1!
1)
1,
1/
b1111 &
b1111 4
12
b0 '
b0 *
b0 -
b0 0
b1 3
b100 "
b100 $
#100
0!
0)
0,
0/
b0 &
b0 4
02
b1 '
b1 *
b1 -
b1 0
b101 "
b101 $
#120
1!
1)
1,
1/
b1111 &
b1111 4
12
b10 '
b10 *
b10 -
b10 0
b110 "
b110 $
#140
0!
0)
0,
0/
b0 &
b0 4
02
b11 '
b11 *
b11 -
b11 0
b111 "
b111 $
#160
1!
1)
1,
1/
b1111 &
b1111 4
12
b0 '
b0 *
b0 -
b0 0
b10 3
b1000 "
b1000 $
#180
0!
0)
0,
0/
b0 &
b0 4
02
b1 '
b1 *
b1 -
b1 0
b1001 "
b1001 $
#200
1!
1)
1,
1/
b1111 &
b1111 4
12
b10 '
b10 *
b10 -
b10 0
b1010 "
b1010 $
#220
0!
0)
0,
0/
b0 &
b0 4
02
b11 '
b11 *
b11 -
b11 0
b1011 "
b1011 $
#240
1!
1)
1,
1/
b1111 &
b1111 4
12
b0 '
b0 *
b0 -
b0 0
b11 3
b1100 "
b1100 $
#260
0!
0)
0,
0/
b0 &
b0 4
02
b1 '
b1 *
b1 -
b1 0
b1101 "
b1101 $
#280
1!
1)
1,
1/
b1111 &
b1111 4
12
b10 '
b10 *
b10 -
b10 0
b1110 "
b1110 $
#300
0!
0)
0,
0/
b0 &
b0 4
02
b11 '
b11 *
b11 -
b11 0
b1111 "
b1111 $
