Semester 3/DSD/Week03/ex2.v
module ex2(a,b,c,d,f1,f2);
input a,b,c,d;
output f1,f2;
nor(k1,b,c);
nor(k2,b,d);
nor(k3,d,d);
nor(k4,a,c,k3);
nor(k5,k1,k2,k4);
nor(f1,k5,k5);
assign g = ((b ~| c) ~| (b ~| d) ~| ((a ~| c )~| (d ~| d))); //notworking
assign f2 = (g ~| g);
endmodule

Semester 3/DSD/Week03/ex2_tb.v
`timescale 1ns/1ns
`include "ex2.v"

module ex2_tb;

reg a,b,c,d;
wire f1,f2;

ex2 ex(a,b,c,d,f1,f2);
initial begin
	$dumpfile("ex2_tb.vcd");
	$dumpvars(0,ex2_tb);
	a=0; b=0; c=0; d=0; #20;
	a=0; b=0; c=0; d=1; #20;
	a=0; b=0; c=1; d=0; #20;
	a=0; b=0; c=1; d=1; #20;
	a=0; b=1; c=0; d=0; #20;
	a=0; b=1; c=0; d=1; #20;
	a=0; b=1; c=1; d=0; #20;
	a=0; b=1; c=1; d=1; #20;
	a=1; b=0; c=0; d=0; #20;
	a=1; b=0; c=0; d=1; #20;
	a=1; b=0; c=1; d=0; #20;
	a=1; b=0; c=1; d=1; #20;
	a=1; b=1; c=0; d=0; #20;
	a=1; b=1; c=0; d=1; #20;
	a=1; b=1; c=1; d=0; #20;
	a=1; b=1; c=1; d=1; #20;
	$display ("Test Complete");
	
	end 
	endmodule

Semester 3/DSD/Week03/ex2_tb.vcd
$date
	Thu Sep  8 14:44:14 2022
$end
$version
	Icarus Verilog
$end
$timescale
	1ns
$end
$scope module ex2_tb $end
$var wire 1 ! f2 $end
$var wire 1 " f1 $end
$var reg 1 # a $end
$var reg 1 $ b $end
$var reg 1 % c $end
$var reg 1 & d $end
$scope module ex $end
$var wire 1 # a $end
$var wire 1 $ b $end
$var wire 1 % c $end
$var wire 1 & d $end
$var wire 1 " f1 $end
$var wire 1 ! f2 $end
$var wire 1 ' g $end
$var wire 1 ( k1 $end
$var wire 1 ) k2 $end
$var wire 1 * k3 $end
$var wire 1 + k4 $end
$var wire 1 , k5 $end
$upscope $end
$upscope $end
$enddefinitions $end
#0
$dumpvars
0,
0+
1*
1)
1(
1'
0&
0%
0$
0#
1"
0!
$end
#20
1+
0)
0*
1&
#40
1)
1*
0(
0+
0&
1%
#60
1!
0"
0'
1,
0)
0*
1&
#80
0"
1,
1*
0+
0&
0%
1$
#100
1"
0,
1+
0*
1&
#120
0"
1,
1*
0+
0&
1%
#140
0*
1&
#160
0!
1"
1'
0,
1*
1(
1)
0&
0%
0$
1#
#180
1!
0'
0)
0*
1&
#200
0!
1'
1)
1*
0(
0&
1%
#220
1!
0"
0'
1,
0)
0*
1&
#240
1*
0&
0%
1$
#260
0*
1&
#280
1*
0&
1%
#300
0*
1&
