Semester 3/DSD/Week03/ex3.v
module ex3(a,b,c,d,e,f);
input a,b,c,d,e;
output f;
assign g= (e&(~a|b));
assign f = (((c~^d)&g)|(~g&~c&d));
endmodule

Semester 3/DSD/Week03/ex3_tb.v
`timescale 1ns/1ns
`include "ex3.v"

module ex3_tb;

reg a,b,c,d,e;
wire f;

ex3 ex(a,b,c,d,e,f);
initial begin
	$dumpfile("ex3_tb.vcd");
	$dumpvars(0,ex3_tb);
	a=0; b=0; c=0; d=0; e=0; #10;
	a=0; b=0; c=0; d=0; e=1; #10;
	a=0; b=0; c=0; d=1; e=0; #10;
	a=0; b=0; c=0; d=1; e=1; #10;
	a=0; b=0; c=1; d=0; e=0; #10;
	a=0; b=0; c=1; d=0; e=1; #10;
	a=0; b=0; c=1; d=1; e=0; #10;
	a=0; b=0; c=1; d=1; e=1; #10;
	a=0; b=1; c=0; d=0; e=0; #10;
	a=0; b=1; c=0; d=0; e=1; #10;
	a=0; b=1; c=0; d=1; e=0; #10;
	a=0; b=1; c=0; d=1; e=1; #10;
	a=0; b=1; c=1; d=0; e=0; #10;
	a=0; b=1; c=1; d=0; e=1; #10;
	a=0; b=1; c=1; d=1; e=0; #10;
	a=0; b=1; c=1; d=1; e=1; #10;
	a=1; b=0; c=0; d=0; e=0; #10;
	a=1; b=0; c=0; d=0; e=1; #10;
	a=1; b=0; c=0; d=1; e=0; #10;
	a=1; b=0; c=0; d=1; e=1; #10;
	a=1; b=0; c=1; d=0; e=0; #10;
	a=1; b=0; c=1; d=0; e=1; #10;
	a=1; b=0; c=1; d=1; e=0; #10;
	a=1; b=0; c=1; d=1; e=1; #10;
	a=1; b=1; c=0; d=0; e=0; #10;
	a=1; b=1; c=0; d=0; e=1; #10;
	a=1; b=1; c=0; d=1; e=0; #10;
	a=1; b=1; c=0; d=1; e=1; #10;
	a=1; b=1; c=1; d=0; e=0; #10;
	a=1; b=1; c=1; d=0; e=1; #10;
	a=1; b=1; c=1; d=1; e=0; #10;
	a=1; b=1; c=1; d=1; e=1; #10;	
	$display ("Test Complete");
	
	end 
	endmodule

Semester 3/DSD/Week03/ex3_tb.vcd
$date
	Thu Sep  8 16:22:51 2022
$end
$version
	Icarus Verilog
$end
$timescale
	1ns
$end
$scope module ex3_tb $end
$var wire 1 ! f $end
$var reg 1 " a $end
$var reg 1 # b $end
$var reg 1 $ c $end
$var reg 1 % d $end
$var reg 1 & e $end
$scope module ex $end
$var wire 1 " a $end
$var wire 1 # b $end
$var wire 1 $ c $end
$var wire 1 % d $end
$var wire 1 & e $end
$var wire 1 ! f $end
$var wire 1 ' g $end
$upscope $end
$upscope $end
$enddefinitions $end
#0
$dumpvars
0'
0&
0%
0$
0#
0"
0!
$end
#10
1!
1'
1&
#20
1!
0'
0&
1%
#30
0!
1'
1&
#40
0'
0&
0%
1$
#50
1'
1&
#60
0'
0&
1%
#70
1!
1'
1&
#80
0!
0'
0&
0%
0$
1#
#90
1!
1'
1&
#100
1!
0'
0&
1%
#110
0!
1'
1&
#120
0'
0&
0%
1$
#130
1'
1&
#140
0'
0&
1%
#150
1!
1'
1&
#160
0!
0'
0&
0%
0$
0#
1"
#170
1&
#180
1!
0&
1%
#190
1&
#200
0!
0&
0%
1$
#210
1&
#220
0&
1%
#230
1&
#240
0&
0%
0$
1#
#250
1!
1'
1&
#260
1!
0'
0&
1%
#270
0!
1'
1&
#280
0'
0&
0%
1$
#290
1'
1&
#300
0'
0&
1%
#310
1!
1'
1&
