Semester 3/DSD/Week03/ex4.v
module ex4(a,b,c,d,f);
input a,b,c,d;
output f;
nor(k1,d,d);
nor(k2,a,a);
nor(k3,c,c);
nor(k4,k2,k3);
nor(f,k1,k4);
endmodule

Semester 3/DSD/Week03/ex4_tb.v
`timescale 1ns/1ns
`include "ex4.v"

module ex4_tb;

reg a,b,c,d;
wire f;

ex4 ex(a,b,c,d,f);
initial begin
	$dumpfile("ex4_tb.vcd");
	$dumpvars(0,ex4_tb);
	a=0; b=0; c=0; d=0; #20;
	a=0; b=0; c=0; d=1; #20;
	a=0; b=0; c=1; d=0; #20;
	a=0; b=0; c=1; d=1; #20;
	a=0; b=1; c=0; d=0; #20;
	a=0; b=1; c=0; d=1; #20;
	a=0; b=1; c=1; d=0; #20;
	a=0; b=1; c=1; d=1; #20;
	a=1; b=0; c=0; d=0; #20;
	a=1; b=0; c=0; d=1; #20;
	a=1; b=0; c=1; d=0; #20;
	a=1; b=0; c=1; d=1; #20;
	a=1; b=1; c=0; d=0; #20;
	a=1; b=1; c=0; d=1; #20;
	a=1; b=1; c=1; d=0; #20;
	a=1; b=1; c=1; d=1; #20;
	$display ("Test Complete");
	
	end 
	endmodule

Semester 3/DSD/Week03/ex4_tb.vcd
$date
	Thu Sep  8 15:15:20 2022
$end
$version
	Icarus Verilog
$end
$timescale
	1ns
$end
$scope module ex4_tb $end
$var wire 1 ! f $end
$var reg 1 " a $end
$var reg 1 # b $end
$var reg 1 $ c $end
$var reg 1 % d $end
$scope module ex $end
$var wire 1 " a $end
$var wire 1 # b $end
$var wire 1 $ c $end
$var wire 1 % d $end
$var wire 1 ! f $end
$var wire 1 & k1 $end
$var wire 1 ' k2 $end
$var wire 1 ( k3 $end
$var wire 1 ) k4 $end
$upscope $end
$upscope $end
$enddefinitions $end
#0
$dumpvars
0)
1(
1'
1&
0%
0$
0#
0"
0!
$end
#20
1!
0&
1%
#40
0!
1&
0(
0%
1$
#60
1!
0&
1%
#80
0!
1&
1(
0%
0$
1#
#100
1!
0&
1%
#120
0!
1&
0(
0%
1$
#140
1!
0&
1%
#160
0!
1&
1(
0'
0%
0$
0#
1"
#180
1!
0&
1%
#200
0!
1)
1&
0(
0%
1$
#220
0&
1%
#240
0)
1&
1(
0%
0$
1#
#260
1!
0&
1%
#280
0!
1)
1&
0(
0%
1$
#300
0&
1%
