Semester 3/DSD/Week01/ae1.v
module ae1(a,b,c,f1,f2);
input a,b,c;
output f1,f2;
and (k1,a,~c);
and (k2, b, c);
and (k3, ~b, ~c);
or (f1, k1,k2,k3);
or (k4, a, ~b, c);
or (k5, a, b, ~c);
or (k6, ~a, b, ~c);
and (f2, k4, k5, k6);
endmodule

Semester 3/DSD/Week01/ae1_tb.v
`timescale 1ns/1ns
`include "ae1.v"

module ae1_tb;

reg a,b,c;
wire f1, f2;

ae1 uut(a,b,c,f1,f2);
initial begin
	$dumpfile("ae1_tb.vcd");
	$dumpvars(0,ae1_tb);
	a=0; 
	b=0; 
	c=0; 
	#20;
	
	a=0; 
	b=0; 
	c=1; 
	#20;
	
	a=0; 
	b=1; 
	c=0; 
	#20;
	
	a=0; 
	b=1; 
	c=1; 
	#20;
	
	a=1; 
	b=0; 
	c=0; 
	#20;
	
	a=1; 
	b=0; 
	c=1; 
	#20;
	
	a=1; 
	b=1; 
	c=0; 
	#20;
	
	a=1; 
	b=1; 
	c=1; 
	#20;	
	$display ("Test Complete");
	
end 
endmodule

Semester 3/DSD/Week01/ae1_tb.vcd
$date
	Thu Aug 25 16:04:22 2022
$end
$version
	Icarus Verilog
$end
$timescale
	1ns
$end
$scope module ae1_tb $end
$var wire 1 ! f2 $end
$var wire 1 " f1 $end
$var reg 1 # a $end
$var reg 1 $ b $end
$var reg 1 % c $end
$scope module uut $end
$var wire 1 # a $end
$var wire 1 $ b $end
$var wire 1 % c $end
$var wire 1 " f1 $end
$var wire 1 ! f2 $end
$var wire 1 & k1 $end
$var wire 1 ' k2 $end
$var wire 1 ( k3 $end
$var wire 1 ) k4 $end
$var wire 1 * k5 $end
$var wire 1 + k6 $end
$upscope $end
$upscope $end
$enddefinitions $end
#0
$dumpvars
1+
1*
1)
1(
0'
0&
0%
0$
0#
1"
1!
$end
#20
0"
0!
0(
0*
1%
#40
0)
1*
0%
1$
#60
1"
1!
1'
1)
1%
#80
1&
1(
1!
0'
1+
0%
0$
1#
#100
0"
0!
0&
0(
0+
1%
#120
1"
1&
1!
1+
0%
1$
#140
0&
1'
1%
