Semester 3/DSD/Week01/ex2.v
module ex2(a,b,c,d,f,g,fb,gb);
input a,b,c,d;
output f,g,fb,gb;
nand (k1,a,b);
xor (f,k1,c,d);
nor (g,b,c,d);
assign fb = (~(a&b)^c^d);
assign gb = ~((b|c)|d);
endmodule

Semester 3/DSD/Week01/ex2_tb.v
`timescale 1ns/1ns
`include "ex2.v"

module ex2_tb;

reg a,b,c,d;
wire f,g,fb,gb;

ex2 ex(a,b,c,d,f,g,fb,gb);
initial begin
	$dumpfile("ex2_tb.vcd");
	$dumpvars(0,ex2_tb);
	a=0; b=0; c=0; d=0; #20;
	a=0; b=0; c=0; d=1; #20;
	a=0; b=0; c=1; d=0; #20;
	a=0; b=0; c=1; d=1; #20;
	a=0; b=1; c=0; d=0; #20;
	a=0; b=1; c=0; d=1; #20;
	a=0; b=1; c=1; d=0; #20;
	a=0; b=1; c=1; d=1; #20;
	a=1; b=0; c=0; d=0; #20;
	a=1; b=0; c=0; d=1; #20;
	a=1; b=0; c=1; d=0; #20;
	a=1; b=0; c=1; d=1; #20;
	a=1; b=1; c=0; d=0; #20;
	a=1; b=1; c=0; d=1; #20;
	a=1; b=1; c=1; d=0; #20;
	a=1; b=1; c=1; d=1; #20;
	$display ("Test Complete");
	
	end 
	endmodule

Semester 3/DSD/Week01/ex2_tb.vcd
$date
	Thu Aug 25 15:35:06 2022
$end
$version
	Icarus Verilog
$end
$timescale
	1ns
$end
$scope module ex2_tb $end
$var wire 1 ! gb $end
$var wire 1 " g $end
$var wire 1 # fb $end
$var wire 1 $ f $end
$var reg 1 % a $end
$var reg 1 & b $end
$var reg 1 ' c $end
$var reg 1 ( d $end
$scope module ex $end
$var wire 1 % a $end
$var wire 1 & b $end
$var wire 1 ' c $end
$var wire 1 ( d $end
$var wire 1 $ f $end
$var wire 1 # fb $end
$var wire 1 " g $end
$var wire 1 ! gb $end
$var wire 1 ) k1 $end
$upscope $end
$upscope $end
$enddefinitions $end
#0
$dumpvars
1)
0(
0'
0&
0%
1$
1#
1"
1!
$end
#20
0!
0$
0"
0#
1(
#40
0(
1'
#60
1$
1#
1(
#80
0(
0'
1&
#100
0$
0#
1(
#120
0(
1'
#140
1$
1#
1(
#160
1!
1"
0(
0'
0&
1%
#180
0!
0$
0"
0#
1(
#200
0(
1'
#220
1$
1#
1(
#240
0#
0$
0)
0(
0'
1&
#260
1$
1#
1(
#280
0(
1'
#300
0$
0#
1(
