Semester 3/DSD/Week09/q1.v
module q1(a,b,c,d,e,f);
input a,b,c,d,e;
output f;
wire [0:15] Y;
dec4to16 s0 ({a,b,c,d},e,Y);
assign f=Y[1] | Y[3] | Y[6] | Y[7] | Y[9] | Y[14] | Y[15];
endmodule

module dec4to16(w,e,y);
input [3:0] w;
input e;
output reg [0:15] y;
always @(w,e)
begin 
	if (e==0) y=0;
	else 
		case (w)
		0: y=16'b1000000000000000; 1: y=16'b0100000000000000;
		2: y=16'b0010000000000000; 3: y=16'b0001000000000000;
		4: y=16'b0000100000000000; 5: y=16'b0000010000000000;
		6: y=16'b0000001000000000; 7: y=16'b0000000100000000;
		8: y=16'b0000000010000000; 9: y=16'b0000000001000000;
		10: y=16'b0000000000100000; 11: y=16'b0000000000010000;
		12: y=16'b0000000000001000; 13: y=16'b0000000000000100;
		14: y=16'b0000000000000010; 15: y=16'b0000000000000001;
		endcase
end
endmodule

Semester 3/DSD/Week09/q1_tb.v
`timescale 1ns/1ns
`include "q1.v"
module q1_tb;
reg a,b,c,d,e;
wire f;
q1 uut(a,b,c,d,e,f);
initial begin	
	$dumpfile("q1_tb.vcd");
	$dumpvars(0,q1_tb);
	a=0; b=0; c=0; d=0; e=1; #20;
	a=0; b=0; c=0; d=1; e=1; #20;
	a=0; b=0; c=1; d=0; e=1; #20;
	a=0; b=0; c=1; d=1; e=1; #20;
	a=0; b=1; c=0; d=0; e=1; #20;
	a=0; b=1; c=0; d=1; e=1; #20;
	a=0; b=1; c=1; d=0; e=1; #20;
	a=0; b=1; c=1; d=1; e=1; #20;
	a=1; b=0; c=0; d=0; e=1; #20;
	a=1; b=0; c=0; d=1; e=1; #20;
	a=1; b=0; c=1; d=0; e=1; #20;
	a=1; b=0; c=1; d=1; e=1; #20;
	a=1; b=1; c=0; d=0; e=1; #20;
	a=1; b=1; c=0; d=1; e=1; #20;
	a=1; b=1; c=1; d=0; e=1; #20;
	a=1; b=1; c=1; d=1; e=1; #20;
	$display ("Test Complete");	
end 
endmodule

Semester 3/DSD/Week09/q1_tb.vcd
$date
	Thu Oct 27 15:04:05 2022
$end
$version
	Icarus Verilog
$end
$timescale
	1ns
$end
$scope module q1_tb $end
$var wire 1 ! f $end
$var reg 1 " a $end
$var reg 1 # b $end
$var reg 1 $ c $end
$var reg 1 % d $end
$var reg 1 & e $end
$scope module uut $end
$var wire 1 " a $end
$var wire 1 # b $end
$var wire 1 $ c $end
$var wire 1 % d $end
$var wire 1 & e $end
$var wire 1 ! f $end
$var wire 16 ' Y [0:15] $end
$scope module s0 $end
$var wire 1 & e $end
$var wire 4 ( w [3:0] $end
$var reg 16 ) y [0:15] $end
$upscope $end
$upscope $end
$upscope $end
$enddefinitions $end
#0
$dumpvars
b1000000000000000 )
b0 (
b1000000000000000 '
1&
0%
0$
0#
0"
0!
$end
#20
1!
b100000000000000 '
b100000000000000 )
b1 (
1%
#40
0!
b10000000000000 '
b10000000000000 )
0%
b10 (
1$
#60
1!
b1000000000000 '
b1000000000000 )
b11 (
1%
#80
0!
b100000000000 '
b100000000000 )
0%
0$
b100 (
1#
#100
b10000000000 '
b10000000000 )
b101 (
1%
#120
1!
b1000000000 '
b1000000000 )
0%
b110 (
1$
#140
b100000000 '
b100000000 )
b111 (
1%
#160
0!
b10000000 '
b10000000 )
0%
0$
0#
b1000 (
1"
#180
1!
b1000000 '
b1000000 )
b1001 (
1%
#200
0!
b100000 '
b100000 )
0%
b1010 (
1$
#220
b10000 '
b10000 )
b1011 (
1%
#240
b1000 '
b1000 )
0%
0$
b1100 (
1#
#260
b100 '
b100 )
b1101 (
1%
#280
1!
b10 '
b10 )
0%
b1110 (
1$
#300
b1 '
b1 )
b1111 (
1%
