Semester 3/DSD/Week09/q2.v
module q2(a,b,c,d,e,F,G,H);
input a,b,c,d,e;
output F,G,H;
wire [0:15] Y;
dec4to16 s0 ({a,b,c,d},e,Y);
assign F = Y[3] | Y[6] | Y[7] | Y[10] | Y[11] | Y[14];
assign G = Y[2] | Y[3] | Y[10] | Y[14];
assign H = Y[0] | Y[1] | Y[3] | Y[7] | Y[14] | Y[15];
endmodule

module dec4to16 (w,e,y);
input [3:0] w;
input e;
output [0:15] y;
wire [0:3] k;
dec2to4 s0 (w[3:2],e,k[0:3]);
dec2to4 s1 (w[1:0],k[0],y[0:3]);
dec2to4 s2 (w[1:0],k[1],y[4:7]);
dec2to4 s3 (w[1:0],k[2],y[8:11]);
dec2to4 s4 (w[1:0],k[3],y[12:15]);
endmodule

module dec2to4 (w,e,y);
input [1:0] w;
input e;
output reg [0:3] y;
always @(w or e)
	if (e==0) y=0;
	else 
		case (w)
		0: y=8;
		1: y=4;
		2: y=2;
		3: y=1;
		endcase
endmodule

Semester 3/DSD/Week09/q2_tb.v
`timescale 1ns/1ns
`include "q2.v"
module q2_tb;
reg a,b,c,d,e;
wire F,G,H;
q2 uut(a,b,c,d,e,F,G,H);
initial begin	
	$dumpfile("q2_tb.vcd");
	$dumpvars(0,q2_tb);
	a=0; b=0; c=0; d=0; e=1; #20;
	a=0; b=0; c=0; d=1; e=1; #20;
	a=0; b=0; c=1; d=0; e=1; #20;
	a=0; b=0; c=1; d=1; e=1; #20;
	a=0; b=1; c=0; d=0; e=1; #20;
	a=0; b=1; c=0; d=1; e=1; #20;
	a=0; b=1; c=1; d=0; e=1; #20;
	a=0; b=1; c=1; d=1; e=1; #20;
	a=1; b=0; c=0; d=0; e=1; #20;
	a=1; b=0; c=0; d=1; e=1; #20;
	a=1; b=0; c=1; d=0; e=1; #20;
	a=1; b=0; c=1; d=1; e=1; #20;
	a=1; b=1; c=0; d=0; e=1; #20;
	a=1; b=1; c=0; d=1; e=1; #20;
	a=1; b=1; c=1; d=0; e=1; #20;
	a=1; b=1; c=1; d=1; e=1; #20;
	$display ("Test Complete");	
end 
endmodule

Semester 3/DSD/Week09/q2_tb.vcd
$date
	Thu Oct 27 15:23:32 2022
$end
$version
	Icarus Verilog
$end
$timescale
	1ns
$end
$scope module q2_tb $end
$var wire 1 ! H $end
$var wire 1 " G $end
$var wire 1 # F $end
$var reg 1 $ a $end
$var reg 1 % b $end
$var reg 1 & c $end
$var reg 1 ' d $end
$var reg 1 ( e $end
$scope module uut $end
$var wire 1 # F $end
$var wire 1 " G $end
$var wire 1 ! H $end
$var wire 1 $ a $end
$var wire 1 % b $end
$var wire 1 & c $end
$var wire 1 ' d $end
$var wire 1 ( e $end
$var wire 16 ) Y [0:15] $end
$scope module s0 $end
$var wire 1 ( e $end
$var wire 4 * w [3:0] $end
$var wire 16 + y [0:15] $end
$var wire 4 , k [0:3] $end
$scope module s0 $end
$var wire 1 ( e $end
$var wire 2 - w [1:0] $end
$var reg 4 . y [0:3] $end
$upscope $end
$scope module s1 $end
$var wire 1 / e $end
$var wire 2 0 w [1:0] $end
$var reg 4 1 y [0:3] $end
$upscope $end
$scope module s2 $end
$var wire 1 2 e $end
$var wire 2 3 w [1:0] $end
$var reg 4 4 y [0:3] $end
$upscope $end
$scope module s3 $end
$var wire 1 5 e $end
$var wire 2 6 w [1:0] $end
$var reg 4 7 y [0:3] $end
$upscope $end
$scope module s4 $end
$var wire 1 8 e $end
$var wire 2 9 w [1:0] $end
$var reg 4 : y [0:3] $end
$upscope $end
$upscope $end
$upscope $end
$upscope $end
$enddefinitions $end
#0
$dumpvars
b0 :
b0 9
08
b0 7
b0 6
05
b0 4
b0 3
02
b1000 1
b0 0
1/
b1000 .
b0 -
b1000 ,
b1000000000000000 +
b0 *
b1000000000000000 )
1(
0'
0&
0%
0$
0#
0"
1!
$end
#20
b100000000000000 )
b100000000000000 +
b100 1
b1 0
b1 3
b1 6
b1 9
b1 *
1'
#40
0!
1"
b10000000000000 )
b10000000000000 +
b10 1
b10 0
b10 3
b10 6
b10 9
0'
b10 *
1&
#60
1#
1!
b1000000000000 )
b1000000000000 +
b1 1
b11 0
b11 3
b11 6
b11 9
b11 *
1'
#80
0!
0#
0"
b1000 4
12
0/
b100000000000 )
b100000000000 +
b0 1
b100 ,
b100 .
b0 0
b0 3
b0 6
b0 9
b1 -
0'
0&
b100 *
1%
#100
b10000000000 )
b10000000000 +
b100 4
b1 0
b1 3
b1 6
b1 9
b101 *
1'
#120
1#
b1000000000 )
b1000000000 +
b10 4
b10 0
b10 3
b10 6
b10 9
0'
b110 *
1&
#140
1!
b100000000 )
b100000000 +
b1 4
b11 0
b11 3
b11 6
b11 9
b111 *
1'
#160
0#
0!
b1000 7
15
02
b10000000 )
b10000000 +
b0 4
b10 ,
b10 .
b0 0
b0 3
b0 6
b0 9
b10 -
0'
0&
0%
b1000 *
1$
#180
b1000000 )
b1000000 +
b100 7
b1 0
b1 3
b1 6
b1 9
b1001 *
1'
#200
1#
1"
b100000 )
b100000 +
b10 7
b10 0
b10 3
b10 6
b10 9
0'
b1010 *
1&
#220
0"
b10000 )
b10000 +
b1 7
b11 0
b11 3
b11 6
b11 9
b1011 *
1'
#240
0#
b1000 :
18
05
b1000 )
b1000 +
b0 7
b1 ,
b1 .
b0 0
b0 3
b0 6
b0 9
b11 -
0'
0&
b1100 *
1%
#260
b100 )
b100 +
b100 :
b1 0
b1 3
b1 6
b1 9
b1101 *
1'
#280
1!
1"
1#
b10 )
b10 +
b10 :
b10 0
b10 3
b10 6
b10 9
0'
b1110 *
1&
#300
0"
0#
b1 )
b1 +
b1 :
b11 0
b11 3
b11 6
b11 9
b1111 *
1'
