Semester 3/DSD/Week10/q3.v
module q3(J,K,Reset,Clock,Q);
input J,K,Reset,Clock;
output reg Q;
always @(posedge Clock)
if (Reset==1) Q<=0;
else Q <= (Q&(~K)) | ((~Q)&J);
endmodule

Semester 3/DSD/Week10/q3_tb.v
`timescale 1ns/1ns
`include "q3.v" 
module q3_tb();
reg J,K,Clock,Reset;
wire Q;

q3 uut(J,K,Reset,Clock,Q);
initial begin
	$dumpfile("q3_tb.vcd");
	$dumpvars(0, q3_tb);
	J=1; K=0; Reset=0; Clock=1; #20;
	J=1; K=0; Reset=0; Clock=0; #20;
	J=0; K=1; Reset=0; Clock=1; #20;
	J=0; K=0; Reset=0; Clock=0; #20;
	J=1; K=1; Reset=0; Clock=1; #20;
	J=1; K=0; Reset=1; Clock=0; #20;
	J=0; K=1; Reset=1; Clock=1; #20;
	J=0; K=0; Reset=1; Clock=0; #20;
	J=1; K=1; Reset=1; Clock=1; #20;
	$display("Test complete");
end
endmodule

Semester 3/DSD/Week10/q3_tb.vcd
$date
	Thu Nov  3 16:29:33 2022
$end
$version
	Icarus Verilog
$end
$timescale
	1ns
$end
$scope module q3_tb $end
$var wire 1 ! Q $end
$var reg 1 " Clock $end
$var reg 1 # J $end
$var reg 1 $ K $end
$var reg 1 % Reset $end
$scope module uut $end
$var wire 1 " Clock $end
$var wire 1 # J $end
$var wire 1 $ K $end
$var wire 1 % Reset $end
$var reg 1 ! Q $end
$upscope $end
$upscope $end
$enddefinitions $end
#0
$dumpvars
0%
0$
1#
1"
x!
$end
#20
0"
#40
0!
1"
1$
0#
#60
0"
0$
#80
1!
1"
1$
1#
#100
0"
1%
0$
#120
0!
1"
1$
0#
#140
0"
0$
#160
1"
1$
1#
