Semester 3/DSD/Week04/ex1.v
module halfadder(x0,y0,c0,s0);
input x0,y0;
output c0,s0;
assign c0 = x0&y0;
assign s0 = x0^y0;
endmodule 

module fulladder(x1,y1,ci1,co1,s1);
input x1,y1,ci1;
output co1,s1;
assign s1 = x1^y1^ci1;
assign co1 = (x1&y1)|(y1&ci1)|(ci1&x1);
endmodule

module dfulladder(x2,y2,ci2,co2,s2);
input x2,y2,ci2;
output co2,s2;
halfadder stage0 (x2,y2,co2_1,s2_1);
halfadder stage1 (co2_1,ci2,co2_2,s2);
assign co2 = co2_1|co2_2;
endmodule

Semester 3/DSD/Week04/ex1_tb.v
`timescale 1ns/1ns
`include "ex1.v"
module ex1_tb;

reg x0,y0,x1,y1,x2,y2,ci1,ci2;
wire c0,s0,co1,s1,co2,s2;

halfadder ha(x0,y0,c0,s0);
fulladder fa(x1,y1,ci1,co1,s1);
dfulladder dfa(x2,y2,ci2,co2,s2);
initial begin
	$dumpfile("ex1_tb.vcd");
	$dumpvars(0,ex1_tb);
	x0=0; y0=0; x1=0; y1=0; ci1=0; x2=0; y2=0; ci2=0; #20;
	x0=0; y0=1; x1=0; y1=0; ci1=1; x2=0; y2=0; ci2=1; #20;
	x0=1; y0=0; x1=0; y1=1; ci1=0; x2=0; y2=1; ci2=0; #20;
	x0=1; y0=1; x1=0; y1=1; ci1=1; x2=0; y2=1; ci2=1; #20;
	x1=1; y1=0; ci1=0; x2=1; y2=0; ci2=0; #20;
	x1=1; y1=0; ci1=1; x2=1; y2=0; ci2=1; #20;
	x1=1; y1=1; ci1=0; x2=1; y2=1; ci2=0; #20;
	x1=1; y1=1; ci1=1; x2=1; y2=1; ci2=1; #20;
	$display ("Test Complete");
end 
endmodule

Semester 3/DSD/Week04/ex1_tb.vcd
$date
	Thu Sep 15 14:07:46 2022
$end
$version
	Icarus Verilog
$end
$timescale
	1ns
$end
$scope module ex1_tb $end
$var wire 1 ! s2 $end
$var wire 1 " s1 $end
$var wire 1 # s0 $end
$var wire 1 $ co2 $end
$var wire 1 % co1 $end
$var wire 1 & c0 $end
$var reg 1 ' ci1 $end
$var reg 1 ( ci2 $end
$var reg 1 ) x0 $end
$var reg 1 * x1 $end
$var reg 1 + x2 $end
$var reg 1 , y0 $end
$var reg 1 - y1 $end
$var reg 1 . y2 $end
$scope module dfa $end
$var wire 1 ( ci2 $end
$var wire 1 $ co2 $end
$var wire 1 + x2 $end
$var wire 1 . y2 $end
$var wire 1 / s2_1 $end
$var wire 1 ! s2 $end
$var wire 1 0 co2_2 $end
$var wire 1 1 co2_1 $end
$scope module stage0 $end
$var wire 1 1 c0 $end
$var wire 1 / s0 $end
$var wire 1 + x0 $end
$var wire 1 . y0 $end
$upscope $end
$scope module stage1 $end
$var wire 1 0 c0 $end
$var wire 1 ! s0 $end
$var wire 1 1 x0 $end
$var wire 1 ( y0 $end
$upscope $end
$upscope $end
$scope module fa $end
$var wire 1 ' ci1 $end
$var wire 1 % co1 $end
$var wire 1 " s1 $end
$var wire 1 * x1 $end
$var wire 1 - y1 $end
$upscope $end
$scope module ha $end
$var wire 1 & c0 $end
$var wire 1 # s0 $end
$var wire 1 ) x0 $end
$var wire 1 , y0 $end
$upscope $end
$upscope $end
$enddefinitions $end
#0
$dumpvars
01
00
0/
0.
0-
0,
0+
0*
0)
0(
0'
0&
0%
0$
0#
0"
0!
$end
#20
1!
1"
1#
1(
1'
1,
#40
0!
1/
0(
1.
0'
1-
0,
1)
#60
1%
1!
0"
1&
0#
1(
1'
1,
#80
0%
0!
1"
0(
0.
1+
0'
0-
1*
#100
1%
1!
0"
1(
1'
#120
1$
11
0/
0(
1.
0'
1-
#140
10
0!
1"
1(
1'
