Semester 3/DSD/Week11/q2.v
module DFF (D, Clock, clear,Q);
input D,clear, Clock;
output reg Q;
always @ (posedge Clock)
begin
	if (clear==0) Q<=0;
	else Q<=D;
end
endmodule

module q2(Q,Clock,clear);
input Clock,clear;
output [4:0] Q;
DFF s0 (~Q[0],Clock,clear,Q[4]);
DFF s1 (Q[4],Clock,clear,Q[3]);
DFF s2 (Q[3],Clock,clear,Q[2]);
DFF s3 (Q[2],Clock,clear,Q[1]);
DFF s4 (Q[1],Clock,clear,Q[0]);
endmodule

Semester 3/DSD/Week11/q2_tb.v
`timescale 1ns/1ns
`include "q2.v"
module q2_tb();
reg Clock,clear;
wire [4:0] Q;
q2 uut(Q,Clock,clear);

always #5 Clock=~Clock;
initial begin
	clear=0; Clock=1;
	#150 $finish;
end
initial begin
	$dumpfile("q2_tb.vcd");
	$dumpvars(0,q2_tb);
	$monitor($time, " clear=%b, Q=%5b", clear, Q );
	#10 clear =1;
end
endmodule

Semester 3/DSD/Week11/q2_tb.vcd
$date
	Thu Nov 17 16:34:13 2022
$end
$version
	Icarus Verilog
$end
$timescale
	1ns
$end
$scope module q2_tb $end
$var wire 5 ! Q [4:0] $end
$var reg 1 " Clock $end
$var reg 1 # clear $end
$scope module uut $end
$var wire 1 " Clock $end
$var wire 1 # clear $end
$var wire 5 $ Q [4:0] $end
$scope module s0 $end
$var wire 1 " Clock $end
$var wire 1 % D $end
$var wire 1 # clear $end
$var reg 1 & Q $end
$upscope $end
$scope module s1 $end
$var wire 1 " Clock $end
$var wire 1 ' D $end
$var wire 1 # clear $end
$var reg 1 ( Q $end
$upscope $end
$scope module s2 $end
$var wire 1 " Clock $end
$var wire 1 ) D $end
$var wire 1 # clear $end
$var reg 1 * Q $end
$upscope $end
$scope module s3 $end
$var wire 1 " Clock $end
$var wire 1 + D $end
$var wire 1 # clear $end
$var reg 1 , Q $end
$upscope $end
$scope module s4 $end
$var wire 1 " Clock $end
$var wire 1 - D $end
$var wire 1 # clear $end
$var reg 1 . Q $end
$upscope $end
$upscope $end
$upscope $end
$enddefinitions $end
#0
$dumpvars
0.
0-
0,
0+
0*
0)
0(
0'
0&
1%
b0 $
0#
1"
b0 !
$end
#5
0"
#10
1'
b10000 !
b10000 $
1&
1"
1#
#15
0"
#20
1)
b11000 !
b11000 $
1(
1"
#25
0"
#30
1+
b11100 !
b11100 $
1*
1"
#35
0"
#40
1-
b11110 !
b11110 $
1,
1"
#45
0"
#50
0%
b11111 !
b11111 $
1.
1"
#55
0"
#60
0'
b1111 !
b1111 $
0&
1"
#65
0"
#70
0)
b111 !
b111 $
0(
1"
#75
0"
#80
0+
b11 !
b11 $
0*
1"
#85
0"
#90
0-
b1 !
b1 $
0,
1"
#95
0"
#100
1%
b0 !
b0 $
0.
1"
#105
0"
#110
1'
b10000 !
b10000 $
1&
1"
#115
0"
#120
1)
b11000 !
b11000 $
1(
1"
#125
0"
#130
1+
b11100 !
b11100 $
1*
1"
#135
0"
#140
1-
b11110 !
b11110 $
1,
1"
#145
0"
#150
0%
b11111 !
b11111 $
1.
1"
