Semester 3/DSD/Week11/q5.v
module q5(Clock, clear, en, Q);
input Clock, clear, en;
output [3:0] Q;
TFF s0 (en | ~en, Clock, clear, Q[0]);
TFF s1 (Q[0]&en | ~en&~Q[0], Clock, clear, Q[1]);
TFF s2 (Q[0]&Q[1]&en | ~Q[1]&~Q[0]&~en , Clock, clear, Q[2]);
TFF s3 (Q[0]&Q[1]&Q[2]&en | ~Q[2]&~Q[1]&~Q[0]&~en, Clock, clear, Q[3]);
endmodule 

module TFF(T,Clock,clear,Q);
input T,Clock,clear;
output reg Q;
always @(negedge Clock or negedge clear)
begin 
	if ( clear==0) Q<=0;
	else if ( T==1) Q<=~Q;
	else Q<=Q;
end
endmodule

Semester 3/DSD/Week11/q5_tb.v
`timescale 1ns/1ns
`include "q5.v" 
module q5_tb();
reg en,Clock,clear; 
wire [3:0] Q;
q5 uut(Clock,clear,en,Q);
initial begin
	$dumpfile("q5_tb.vcd");
	$dumpvars(0, q5_tb);
	Clock=0;
	forever #10 Clock = ~Clock;
end
initial begin
	en = 0;
	clear = 0; #20;
	clear = 1; #300;
	en = 1;
	clear = 0; #30;
	clear = 1; #300;
    $display("Test complete");
	$finish;
end
endmodule

Semester 3/DSD/Week11/q5_tb.vcd
$date
	Wed Nov 23 20:38:37 2022
$end
$version
	Icarus Verilog
$end
$timescale
	1ns
$end
$scope module q5_tb $end
$var wire 4 ! Q [3:0] $end
$var reg 1 " Clock $end
$var reg 1 # clear $end
$var reg 1 $ en $end
$scope module uut $end
$var wire 1 % Clock $end
$var wire 4 & Q [3:0] $end
$var wire 1 ' clear $end
$var wire 1 ( en $end
$scope module s0 $end
$var wire 1 % Clock $end
$var wire 1 ) T $end
$var wire 1 ' clear $end
$var reg 1 * Q $end
$upscope $end
$scope module s1 $end
$var wire 1 % Clock $end
$var wire 1 + T $end
$var wire 1 ' clear $end
$var reg 1 , Q $end
$upscope $end
$scope module s2 $end
$var wire 1 % Clock $end
$var wire 1 - T $end
$var wire 1 ' clear $end
$var reg 1 . Q $end
$upscope $end
$scope module s3 $end
$var wire 1 % Clock $end
$var wire 1 / T $end
$var wire 1 ' clear $end
$var reg 1 0 Q $end
$upscope $end
$upscope $end
$upscope $end
$enddefinitions $end
#0
$dumpvars
00
1/
0.
1-
0,
1+
0*
1)
0(
0'
b0 &
0%
0$
0#
0"
b0 !
$end
#10
1"
1%
#20
0-
0/
0+
10
1.
1,
1*
b1111 !
b1111 &
0"
0%
1#
1'
#30
1"
1%
#40
1+
0*
b1110 !
b1110 &
0"
0%
#50
1"
1%
#60
0+
0,
1*
b1101 !
b1101 &
0"
0%
#70
1"
1%
#80
1-
1+
0*
b1100 !
b1100 &
0"
0%
#90
1"
1%
#100
0-
0+
0.
1,
1*
b1011 !
b1011 &
0"
0%
#110
1"
1%
#120
1+
0*
b1010 !
b1010 &
0"
0%
#130
1"
1%
#140
0+
0,
1*
b1001 !
b1001 &
0"
0%
#150
1"
1%
#160
1-
1/
1+
0*
b1000 !
b1000 &
0"
0%
#170
1"
1%
#180
0-
0/
0+
00
1.
1,
1*
b111 !
b111 &
0"
0%
#190
1"
1%
#200
1+
0*
b110 !
b110 &
0"
0%
#210
1"
1%
#220
0+
0,
1*
b101 !
b101 &
0"
0%
#230
1"
1%
#240
1-
1+
0*
b100 !
b100 &
0"
0%
#250
1"
1%
#260
0-
0+
0.
1,
1*
b11 !
b11 &
0"
0%
#270
1"
1%
#280
1+
0*
b10 !
b10 &
0"
0%
#290
1"
1%
#300
0+
0,
1*
b1 !
b1 &
0"
0%
#310
1"
1%
#320
0*
b0 !
b0 &
0+
0"
0%
0#
0'
1$
1(
#330
1"
1%
#340
0"
0%
#350
1"
1%
1#
1'
#360
1+
1*
b1 !
b1 &
0"
0%
#370
1"
1%
#380
0+
1,
0*
b10 !
b10 &
0"
0%
#390
1"
1%
#400
1-
1+
1*
b11 !
b11 &
0"
0%
#410
1"
1%
#420
0-
0+
1.
0,
0*
b100 !
b100 &
0"
0%
#430
1"
1%
#440
1+
1*
b101 !
b101 &
0"
0%
#450
1"
1%
#460
0+
1,
0*
b110 !
b110 &
0"
0%
#470
1"
1%
#480
1/
1-
1+
1*
b111 !
b111 &
0"
0%
#490
1"
1%
#500
0/
0-
0+
10
0.
0,
0*
b1000 !
b1000 &
0"
0%
#510
1"
1%
#520
1+
1*
b1001 !
b1001 &
0"
0%
#530
1"
1%
#540
0+
1,
0*
b1010 !
b1010 &
0"
0%
#550
1"
1%
#560
1-
1+
1*
b1011 !
b1011 &
0"
0%
#570
1"
1%
#580
0-
0+
1.
0,
0*
b1100 !
b1100 &
0"
0%
#590
1"
1%
#600
1+
1*
b1101 !
b1101 &
0"
0%
#610
1"
1%
#620
0+
1,
0*
b1110 !
b1110 &
0"
0%
#630
1"
1%
#640
1/
1-
1+
1*
b1111 !
b1111 &
0"
0%
